awslabs/__init__.py
awslabs/aws_bedrock_custom_model_import_mcp_server/__init__.py
awslabs/aws_bedrock_custom_model_import_mcp_server/client.py
awslabs/aws_bedrock_custom_model_import_mcp_server/llm_context.py
awslabs/aws_bedrock_custom_model_import_mcp_server/models.py
awslabs/aws_bedrock_custom_model_import_mcp_server/prompts.py
awslabs/aws_bedrock_custom_model_import_mcp_server/server.py
awslabs/aws_bedrock_custom_model_import_mcp_server/services/__init__.py
awslabs/aws_bedrock_custom_model_import_mcp_server/services/imported_model_service.py
awslabs/aws_bedrock_custom_model_import_mcp_server/services/model_import_service.py
awslabs/aws_bedrock_custom_model_import_mcp_server/tools/create_model_import_job.py
awslabs/aws_bedrock_custom_model_import_mcp_server/tools/delete_imported_model.py
awslabs/aws_bedrock_custom_model_import_mcp_server/tools/get_imported_model.py
awslabs/aws_bedrock_custom_model_import_mcp_server/tools/get_model_import_job.py
awslabs/aws_bedrock_custom_model_import_mcp_server/tools/list_imported_models.py
awslabs/aws_bedrock_custom_model_import_mcp_server/tools/list_model_import_jobs.py
awslabs/aws_bedrock_custom_model_import_mcp_server/utils/__init__.py
awslabs/aws_bedrock_custom_model_import_mcp_server/utils/aws.py
awslabs/aws_bedrock_custom_model_import_mcp_server/utils/config.py
awslabs/aws_bedrock_custom_model_import_mcp_server/utils/consts.py
awslabs/aws_bedrock_custom_model_import_mcp_server/utils/matching.py
awslabs_aws_bedrock_custom_model_import_mcp_server-0.0.11.dist-info/METADATA
awslabs_aws_bedrock_custom_model_import_mcp_server-0.0.11.dist-info/WHEEL
awslabs_aws_bedrock_custom_model_import_mcp_server-0.0.11.dist-info/entry_points.txt
awslabs_aws_bedrock_custom_model_import_mcp_server-0.0.11.dist-info/licenses/LICENSE
awslabs_aws_bedrock_custom_model_import_mcp_server-0.0.11.dist-info/licenses/NOTICE
awslabs_aws_bedrock_custom_model_import_mcp_server-0.0.11.dist-info/RECORD
