Metadata-Version: 2.4
Name: awslabs.aws-bedrock-custom-model-import-mcp-server
Version: 0.0.11
Summary: An AWS Labs Model Context Protocol (MCP) server for Bedrock Custom Model Import
Project-URL: homepage, https://awslabs.github.io/mcp/
Project-URL: docs, https://awslabs.github.io/mcp/servers/aws-bedrock-custom-model-import-mcp-server/
Project-URL: documentation, https://awslabs.github.io/mcp/servers/aws-bedrock-custom-model-import-mcp-server/
Project-URL: repository, https://github.com/awslabs/mcp.git
Project-URL: changelog, https://github.com/awslabs/mcp/blob/main/src/aws-bedrock-custom-model-import-mcp-server/CHANGELOG.md
Author: Amazon Web Services
Author-email: AWSLabs MCP <203918161+awslabs-mcp@users.noreply.github.com>, saidrhs <sdarahas@amazon.com>
License-Expression: Apache-2.0
License-File: LICENSE
License-File: NOTICE
Classifier: License :: OSI Approved :: Apache Software License
Classifier: Operating System :: OS Independent
Classifier: Programming Language :: Python
Classifier: Programming Language :: Python :: 3
Classifier: Programming Language :: Python :: 3.10
Classifier: Programming Language :: Python :: 3.11
Classifier: Programming Language :: Python :: 3.12
Classifier: Programming Language :: Python :: 3.13
Requires-Python: >=3.10
Requires-Dist: boto3>=1.28.0
Requires-Dist: fastmcp>=2.14.0
Requires-Dist: loguru>=0.7.0
Requires-Dist: pydantic>=2.0.0
Requires-Dist: python-levenshtein>=0.21.0
Requires-Dist: thefuzz>=0.19.0
